README.md
setup.cfg
setup.py
mewtwo/RiskDataframe.py
mewtwo/__init__.py
mewtwo.egg-info/PKG-INFO
mewtwo.egg-info/SOURCES.txt
mewtwo.egg-info/dependency_links.txt
mewtwo.egg-info/not-zip-safe
mewtwo.egg-info/top_level.txt