Metadata-Version: 1.0
Name: mewtwo
Version: 1.0.1
Summary: mewtwo is created from Python Packaging Starting Kit - Simple Structure to creater your own package - for training purposes!
Home-page: https://github.com/palizmun/mewtwo_group_D.git
Author: Palizmun - Group D
Author-email: paliz.mungkaladung@student.ie.edu
License: MIT
Platform: UNKNOWN
